rest_framework_word_filter/__init__.py
rest_framework_word_filter/apps.py
rest_framework_word_filter/filter.py
rest_framework_word_filter/models.py
rest_framework_word_filter/tests.py
djangorestframework_word_filter-0.2.0.dist-info/METADATA
djangorestframework_word_filter-0.2.0.dist-info/WHEEL
djangorestframework_word_filter-0.2.0.dist-info/top_level.txt
djangorestframework_word_filter-0.2.0.dist-info/RECORD
